imgprocessing/__init__.py
imgprocessing/myfunctions.py
ImgUtilsCust-0.1.0.dist-info/METADATA
ImgUtilsCust-0.1.0.dist-info/WHEEL
ImgUtilsCust-0.1.0.dist-info/top_level.txt
ImgUtilsCust-0.1.0.dist-info/RECORD
